rndtools/__init__.py
rndtools/io.py
rndtools/keras_callbacks.py
rndtools/keras_dataset_generator.py
rndtools/peakdetect.py
rndtools/train.py
rndtools-3.0.1.dist-info/DESCRIPTION.rst
rndtools-3.0.1.dist-info/METADATA
rndtools-3.0.1.dist-info/RECORD
rndtools-3.0.1.dist-info/WHEEL
rndtools-3.0.1.dist-info/metadata.json
rndtools-3.0.1.dist-info/top_level.txt
