Metadata-Version: 2.0
Name: rndtools
Version: 3.0.1
Summary: R&D tools
Home-page: https://gitlab.com/identt-rnd/rnd-tools
Author: Damian Mirecki
Author-email: damian.mirecki@identt.pl
License: UNKNOWN
Platform: UNKNOWN
Classifier: Development Status :: 4 - Beta
Classifier: Intended Audience :: Developers
Classifier: Programming Language :: Python :: 2
Classifier: Programming Language :: Python :: 2.7
Classifier: Programming Language :: Python :: 3
Classifier: Programming Language :: Python :: 3.5
Classifier: Programming Language :: Python :: 3.6
Requires-Dist: numpy (>=1.10)
Requires-Dist: scipy (>=0.11.0)
Requires-Dist: matplotlib (>=1.4)
Requires-Dist: keras (>=2.0)
Requires-Dist: click (>=5.0)
Requires-Dist: contexttimer (>=0.3.3)
Requires-Dist: hickle (>=2.1.0)
Requires-Dist: scikit-learn (>=0.18)
Requires-Dist: six (>=1.11)
Requires-Dist: pathos (>=0.2)
Requires-Dist: tqdm (>=4.19)
